abqos/__init__.py
abqos/abqos.py
abqos-1.0.0.dist-info/METADATA
abqos-1.0.0.dist-info/WHEEL
abqos-1.0.0.dist-info/top_level.txt
abqos-1.0.0.dist-info/RECORD
